{"type":"PR","pr":{"number":46,"head":"159ae510dfc5a112ede88a9d7bfe70ad2eb0aee8"},"user":"Artyom Lyubchuk","status":"pending_publish","branch":"cms/cupboard/почему-люди-неправильно-понимают-друг-друга-видос.md","collection":"cupboard","commitMessage":"Create Шкаф “почему-люди-неправильно-понимают-друг-друга-видос.md”","title":"Почему люди неправильно понимают друг друга? (видос)","description":"No Description!","objects":{"entry":{"path":"cupboard/почему-люди-неправильно-понимают-друг-друга-видос.md.md","sha":"f3371e7b196738932f128ff3789b41cb5ee4721d"},"files":[]},"timeStamp":"2020-04-11T16:45:27.162Z","version":"1"}