{"type":"PR","pr":{"number":36,"head":"998f591002cbd587d03ea273c4784148475fe8fa"},"user":"Artyom Lyubchuk","status":"pending_review","branch":"cms/blog/2020-01-09-десяток-способов-узнать-что-не-работает.md","collection":"blog","commitMessage":"Update Публикации “2020-01-09-десяток-способов-узнать-что-не-работает.md”","title":"Десяток способов узнать, что не работает","description":"No Description!","objects":{"entry":{"path":"content/2020-01-09-десяток-способов-узнать-что-не-работает.md.md","sha":"f03664c3e41dcadc6b7908a9d9ea7fe01329306f"},"files":[]},"timeStamp":"2020-03-10T19:55:00.998Z","version":"1"}