{"type":"PR","pr":{"number":44,"head":"58a0178ad4c059045696cb7b2786823a9e624f23"},"user":"Artyom Lyubchuk","status":"pending_review","branch":"cms/blog/2020-04-08-приходить-к-решениям-а-не-принимать-их.md","collection":"blog","commitMessage":"Create Публикации “2020-04-08-приходить-к-решениям-а-не-принимать-их.md”","title":"Приходить к решениям, а не принимать их","description":"No Description!","objects":{"entry":{"path":"content/2020-04-08-приходить-к-решениям-а-не-принимать-их.md.md","sha":"3439f8d19651926e1cd86a524bd49d0f877b46b3"},"files":[{"path":"static/assets/come-to-decision.jpg","sha":"ab9363e73af032b620040f679a9ac01f3c7fdef3"}]},"timeStamp":"2020-04-11T16:22:05.532Z","version":"1"}