{"type":"PR","pr":{"number":62,"head":"e50373d551253408334543612b522242722b190e"},"user":"Artyom Lyubchuk","status":"pending_publish","branch":"cms/blog/2021-06-07-знаний-больше-чем-осознания-и-понимания.md","collection":"blog","commitMessage":"Create Публикации “2021-06-07-знаний-больше-чем-осознания-и-понимания.md”","title":"\"Точно!\" Про осознание и знания","description":"No Description!","objects":{"entry":{"path":"content/2021-06-07-знаний-больше-чем-осознания-и-понимания.md.md","sha":"20ace5b465b3b00121bbcaae9477218efd514bb5"},"files":[{"path":"static/assets/self-awareness-1080x675.jpeg","sha":"8dfc01486f6993c88db7ecadf34d145538c9503d"}]},"timeStamp":"2021-06-08T07:13:24.564Z","version":"1"}