{"type":"PR","pr":{"number":74,"head":"75e3f498c153c184be6add9196679b845f7c5cd8"},"user":"Artyom Lyubchuk","status":"draft","branch":"cms/blog/2021-07-23-регулярная-головная-боль.md","collection":"blog","commitMessage":"Create Публикации “2021-07-23-регулярная-головная-боль.md”","title":"Регулярная головная боль","description":"No Description!","objects":{"entry":{"path":"content/2021-07-23-регулярная-головная-боль.md.md","sha":"f4f3b861544166aeb084431af27a847d4e590c53"},"files":[]},"timeStamp":"2021-07-23T07:59:47.753Z","version":"1"}